{
  "reference": {
    "book": "Deuteronomy",
    "citation": "27:11-26",
    "label": "Deuteronomy 27:11-26",
    "slug": "deuteronomy-27-11-26"
  },
  "section_title": "Curses Pronounced from Ebal",
  "versions": [
    {
      "label": "BSB",
      "paragraphs": [
        "11 On that day Moses commanded the people: 12 \u201cWhen you have crossed the Jordan, these tribes shall stand on Mount Gerizim to bless the people: Simeon, Levi, Judah, Issachar, Joseph, and Benjamin. 13 And these tribes shall stand on Mount Ebal to deliver the curse: Reuben, Gad, Asher, Zebulun, Dan, and Naphtali.",
        "14 Then the Levites shall proclaim in a loud voice to every Israelite:",
        "15 \u2018Cursed is the man who makes a carved idol or molten image\u2014an abomination to the LORD, the work of the hands of a craftsman\u2014and sets it up in secret.\u2019",
        "And let all the people say, \u2018Amen!\u2019",
        "16 \u2018Cursed is he who dishonors his father or mother.\u2019",
        "And let all the people say, \u2018Amen!\u2019",
        "17 \u2018Cursed is he who moves his neighbor\u2019s boundary stone.\u2019",
        "And let all the people say, \u2018Amen!\u2019",
        "18 \u2018Cursed is he who lets a blind man wander in the road.\u2019",
        "And let all the people say, \u2018Amen!\u2019",
        "19 \u2018Cursed is he who withholds justice from the foreigner, the fatherless, or the widow.\u2019",
        "And let all the people say, \u2018Amen!\u2019",
        "20 \u2018Cursed is he who sleeps with his father\u2019s wife, for he has violated his father\u2019s marriage bed.\u2019",
        "And let all the people say, \u2018Amen!\u2019",
        "21 \u2018Cursed is he who lies with any animal.\u2019",
        "And let all the people say, \u2018Amen!\u2019",
        "22 \u2018Cursed is he who sleeps with his sister, the daughter of his father or the daughter of his mother.\u2019",
        "And let all the people say, \u2018Amen!\u2019",
        "23 \u2018Cursed is he who sleeps with his mother-in-law.\u2019",
        "And let all the people say, \u2018Amen!\u2019",
        "24 \u2018Cursed is he who strikes down his neighbor in secret.\u2019",
        "And let all the people say, \u2018Amen!\u2019",
        "25 \u2018Cursed is he who accepts a bribe to kill an innocent person.\u2019",
        "And let all the people say, \u2018Amen!\u2019",
        "26 \u2018Cursed is he who does not put the words of this law into practice.\u2019",
        "And let all the people say, \u2018Amen!\u2019"
      ]
    }
  ],
  "context_lines": [
    "In **Deuteronomy 27**, this section should be read within the flow of the chapter and the larger movement of Deuteronomy."
  ],
  "common_interpretation_lines": [
    "A common reading of **Curses Pronounced from Ebal** is that it should be interpreted in light of the chapter's full narrative movement rather than as an isolated proof text.",
    "",
    "Where interpreters differ on details, the immediate setting in **Deuteronomy 27** remains the first control on meaning."
  ],
  "deeper_study": []
}
